pyinit/__init__.py
pyinit/build.py
pyinit/check.py
pyinit/clean.py
pyinit/create.py
pyinit/format.py
pyinit/graph.py
pyinit/info.py
pyinit/init.py
pyinit/install.py
pyinit/main.py
pyinit/release.py
pyinit/run.py
pyinit/test.py
pyinit/uninstall.py
pyinit/update.py
pyinit/utils.py
pyinit/venv.py
pyinit/wrappers.py
pyinit/_templates/pyproject.toml
pyinit_tool-1.0.14.dist-info/licenses/LICENSE
pyinit_tool-1.0.14.dist-info/METADATA
pyinit_tool-1.0.14.dist-info/WHEEL
pyinit_tool-1.0.14.dist-info/entry_points.txt
pyinit_tool-1.0.14.dist-info/top_level.txt
pyinit_tool-1.0.14.dist-info/RECORD
