Metadata-Version: 2.4
Name: pyinit-tool
Version: 1.0.14
Summary: A tool for creating and managing Python projects
Author-email: Karim <kwkkna3@gmail.com>
Requires-Python: >=3.10
License-File: LICENSE
Requires-Dist: rich
Requires-Dist: tomli
Requires-Dist: tomli-w
Requires-Dist: importlib-resources
Provides-Extra: dev
Requires-Dist: pytest; extra == "dev"
Requires-Dist: pytest-mock; extra == "dev"
Dynamic: license-file
